distributions/Binomialdistribution.py
distributions/Gaussiandistribution.py
distributions/Generaldistribution.py
distributions/__init__.py
minimal_stats-1.0.0.dist-info/LICENSE
minimal_stats-1.0.0.dist-info/METADATA
minimal_stats-1.0.0.dist-info/WHEEL
minimal_stats-1.0.0.dist-info/top_level.txt
minimal_stats-1.0.0.dist-info/RECORD
