Metadata-Version: 2.1
Name: minimal-stats
Version: 1.0.0
Summary: A small package for statistical distributions
Home-page: https://github.com/ashishlamsal/minimal-stats.git
Author: ASHISH LAMSAL
Author-email: ashishlamsal.me@gmail.com
License: UNKNOWN
Project-URL: Bug Tracker, https://github.com/ashishlamsal/minimal-stats/issues
Platform: UNKNOWN
Classifier: Programming Language :: Python
Classifier: Programming Language :: Python :: 3.8
Classifier: Programming Language :: Python :: 3.9
Classifier: License :: OSI Approved :: MIT License
Classifier: Operating System :: OS Independent
Requires-Python: >=3.8
License-File: LICENSE
Requires-Dist: matplotlib
